trelent_data_ingestion_sdk/__init__.py
trelent_data_ingestion_sdk/client.py
trelent_data_ingestion_sdk/config.py
trelent_data_ingestion_sdk/fragment.py
trelent_data_ingestion_sdk/models.py
trelent_data_ingestion-0.1.3.dist-info/METADATA
trelent_data_ingestion-0.1.3.dist-info/WHEEL
trelent_data_ingestion-0.1.3.dist-info/top_level.txt
trelent_data_ingestion-0.1.3.dist-info/RECORD
