Metadata-Version: 2.4
Name: trelent-data-ingestion
Version: 0.1.3
Summary: Python SDK for the Trelent Data Ingestion API
Requires-Python: >=3.9
Requires-Dist: pydantic<3,>=2.11.0
Requires-Dist: requests<3,>=2.31.0
Requires-Dist: typing-extensions>=4.8.0
